wonkaai/__init__.py
wonkaai/Chat/__init__.py
wonkaai/Chat/Chat.py
wonkaai/Chat/ChatFunction.py
wonkaai/Chat/ChatFunctionMultiple.py
wonkaai/DocReader/__init__.py
wonkaai/DocReader/DocReader.py
wonkaai/MailToMail/__init__.py
wonkaai/MailToMail/MailToMail.py
wonkaai/Prompt/__init__.py
wonkaai/Prompt/standalone_question.py
wonkaai/ResultAnalyser/__init__.py
wonkaai/ResultAnalyser/ResultAnalyser.py
wonkaai/TopicToTopic/__init__.py
wonkaai/Vectorizer/__init__.py
wonkaai/Vectorizer/Vectorizer.py
wonkaai/Vectorizer/VectorizerCS.py
wonkaai-0.2.5.dist-info/METADATA
wonkaai-0.2.5.dist-info/WHEEL
wonkaai-0.2.5.dist-info/RECORD
